numpyro_ncx2/__init__.py
numpyro_ncx2/ncx2.py
numpyro_ncx2/numpyro_ncx2_version.py
numpyro_ncx2-0.0.3.dist-info/LICENSE
numpyro_ncx2-0.0.3.dist-info/METADATA
numpyro_ncx2-0.0.3.dist-info/WHEEL
numpyro_ncx2-0.0.3.dist-info/top_level.txt
numpyro_ncx2-0.0.3.dist-info/zip-safe
numpyro_ncx2-0.0.3.dist-info/RECORD
