Metadata-Version: 2.1
Name: numpyro-ncx2
Version: 0.0.3
Summary: A non-central chi-squared distribution for numpyro
Home-page: https://github.com/one-datum/numpyro-ncx2
Author: Dan Foreman-Mackey
Author-email: foreman.mackey@gmail.com
Maintainer: Dan Foreman-Mackey
Maintainer-email: foreman.mackey@gmail.com
License: Apache 2.0
Classifier: Development Status :: 5 - Production/Stable
Classifier: Intended Audience :: Developers
Classifier: Intended Audience :: Science/Research
Classifier: License :: OSI Approved :: Apache Software License
Classifier: Operating System :: OS Independent
Classifier: Programming Language :: Python
Classifier: Programming Language :: Python :: 3
Requires-Python: >=3.6
License-File: LICENSE
Requires-Dist: tensorflow-probability
Requires-Dist: numpyro
Requires-Dist: jax
Provides-Extra: test
Requires-Dist: pytest (>=3.6) ; extra == 'test'
